crim.py
commonregex_improved-1.0.2.dist-info/METADATA
commonregex_improved-1.0.2.dist-info/LICENSE
commonregex_improved-1.0.2.dist-info/WHEEL
commonregex_improved-1.0.2.dist-info/RECORD
