Metadata-Version: 2.1
Name: commonregex-improved
Version: 1.0.2
Summary: An improved version of original commonregex. Find all dates, times, emails, phone numbers, links, emails, ip addresses, prices, bitcoin address, and more in a string.
Home-page: https://github.com/brootware/commonregex-improved
License: MIT
Author: brootware
Author-email: brootware@outlook.com
Requires-Python: >=3.7,<4.0
Classifier: Development Status :: 5 - Production/Stable
Classifier: Intended Audience :: Developers
Classifier: Intended Audience :: Information Technology
Classifier: License :: OSI Approved :: MIT License
Classifier: Operating System :: OS Independent
Classifier: Programming Language :: Python :: 3
Classifier: Programming Language :: Python :: 3.7
Classifier: Programming Language :: Python :: 3.8
Classifier: Programming Language :: Python :: 3.9
Classifier: Programming Language :: Python :: 3.10
Classifier: Programming Language :: Python :: 3.11
Classifier: Programming Language :: Python :: 3
Classifier: Programming Language :: Python :: 3.7
Classifier: Programming Language :: Python :: 3.8
Classifier: Programming Language :: Python :: 3.9
Classifier: Topic :: Security
Classifier: Topic :: Software Development :: Libraries :: Python Modules
Classifier: Topic :: Text Processing :: General
Requires-Dist: regex (>=2022.4.24,<2023.0.0)
Project-URL: Repository, https://github.com/brootware/commonregex-improved
